foliant/meta_commands/collect_test_data.py
foliantcontrib.testcoverage-0.1.1.dist-info/LICENSE
foliantcontrib.testcoverage-0.1.1.dist-info/METADATA
foliantcontrib.testcoverage-0.1.1.dist-info/WHEEL
foliantcontrib.testcoverage-0.1.1.dist-info/top_level.txt
foliantcontrib.testcoverage-0.1.1.dist-info/RECORD
