Metadata-Version: 2.1
Name: foliantcontrib.testcoverage
Version: 0.1.1
Summary: Foliant Meta Command which collects test data.
Home-page: https://github.com/foliant-docs/foliantcontrib.testcoverage
Author: Daniil Minukhin
Author-email: ddddsa@gmail.com
License: MIT
Platform: any
Classifier: Development Status :: 5 - Production/Stable
Classifier: Environment :: Console
Classifier: Intended Audience :: Developers
Classifier: License :: OSI Approved :: MIT License
Classifier: Operating System :: OS Independent
Classifier: Programming Language :: Python
Classifier: Topic :: Documentation
Classifier: Topic :: Utilities
Requires-Dist: foliant (>=1.0.4)
Requires-Dist: foliantcontrib.meta
